pypes/__init__.py
pypes/mixins.py
pypes/printers.py
pypes/text.py
pypes/typing.py
pypes-0.3.1.dist-info/METADATA
pypes-0.3.1.dist-info/WHEEL
pypes-0.3.1.dist-info/licenses/LICENSE
pypes-0.3.1.dist-info/RECORD
