Metadata-Version: 2.3
Name: Pypes
Version: 0.3.1
Summary: A toolset for piping values between functions, with optional shell-like text-processing tools.
Project-URL: Homepage, https://github.com/faelin/pypes
Project-URL: Issues, https://github.com/faelin/pypes/issues
Author-email: Faelin <faelin.codes@gmail.com>
License-File: LICENSE
Classifier: License :: OSI Approved :: MIT License
Classifier: Operating System :: OS Independent
Classifier: Programming Language :: Python :: 3
Classifier: Programming Language :: Python :: 3.7
Classifier: Programming Language :: Python :: 3.8
Classifier: Programming Language :: Python :: 3.9
Classifier: Programming Language :: Python :: 3.10
Classifier: Programming Language :: Python :: 3.11
Classifier: Programming Language :: Python :: 3.12
Requires-Python: >=3.7
